{"description":"","name":"Special","data":[{"description":"PvE: Jagged Edge + Heavy Guard + Relentless Strikes + Vorpal/Whirlwind Blade\nPvP: Anything, You one heavy everything","hash":2782325302,"name":"","plugs":[[3666208348],[2349202967],[1749209109],[1546637391,3913600130]],"tags":["GodPVE"]},{"description":"PvE: Jagged Edge + Heavy Guard + Relentless Strikes + Vorpal/Whirlwind Blade\nPvP: Anything, You one heavy everything","hash":2782325302,"name":"","plugs":[[2349202967],[1749209109],[1546637391,3913600130]],"tags":["PVE"]},{"description":"PvE: Jagged Edge + Heavy Guard + Relentless Strikes + Vorpal/Whirlwind Blade\nPvP: Anything, You one heavy everything","hash":2782325302,"name":"","plugs":[[2349202967],[1546637391,3913600130]],"tags":["PVE"]},{"description":"PvE: Jagged Edge + Heavy Guard + Relentless Strikes + Vorpal/Whirlwind Blade\nPvP: Anything, You one heavy everything","hash":2782325302,"name":"","plugs":[[2349202967],[1749209109]],"tags":["PVE"]},{"description":"PvE: Jagged Edge + Swordmasters Guard + Relentless Strikes + En Garde\nPvP: You’re a Hunter begging for a lightweight weapon, you’re using this for dodge cooldown reduction and to do the funny run\nEn Guarde best in slot for PvP, but ya know, OFA could be a lot of fun in PvE.","hash":2782325300,"name":"","plugs":[[2827049491],[269888150],[1749209109],[1685431615]],"tags":["GodPVE"]},{"description":"PvE: Jagged Edge + Swordmasters Guard + Relentless Strikes + En Garde\nPvP: You’re a Hunter begging for a lightweight weapon, you’re using this for dodge cooldown reduction and to do the funny run\nEn Guarde best in slot for PvP, but ya know, OFA could be a lot of fun in PvE.","hash":2782325300,"name":"","plugs":[[269888150],[1749209109],[1685431615]],"tags":["PVE"]},{"description":"PvE: Jagged Edge + Swordmasters Guard + Relentless Strikes + En Garde\nPvP: You’re a Hunter begging for a lightweight weapon, you’re using this for dodge cooldown reduction and to do the funny run\nEn Guarde best in slot for PvP, but ya know, OFA could be a lot of fun in PvE.","hash":2782325300,"name":"","plugs":[[269888150],[1685431615]],"tags":["PVE"]},{"description":"PvE: Jagged Edge + Swordmasters Guard + Relentless Strikes + En Garde\nPvP: You’re a Hunter begging for a lightweight weapon, you’re using this for dodge cooldown reduction and to do the funny run\nEn Guarde best in slot for PvP, but ya know, OFA could be a lot of fun in PvE.","hash":2782325300,"name":"","plugs":[[269888150],[1749209109]],"tags":["PVE"]},{"description":"PvE: Jagged + Infinite Guard + Relentless Strikes + Surrounded/Counterattack/Flash Counter\nPvP: Any, you 1 heavy anything in the game","hash":2782325301,"name":"","plugs":[[3666208348],[2363751990],[1749209109],[3708227201,3016987351,2244851822]],"tags":["GodPVE"]},{"description":"PvE: Jagged + Infinite Guard + Relentless Strikes + Surrounded/Counterattack/Flash Counter\nPvP: Any, you 1 heavy anything in the game","hash":2782325301,"name":"","plugs":[[2363751990],[1749209109],[3708227201,3016987351,2244851822]],"tags":["GodPVE"]},{"description":"PvE: Jagged + Infinite Guard + Relentless Strikes + Surrounded/Counterattack/Flash Counter\nPvP: Any, you 1 heavy anything in the game","hash":2782325301,"name":"","plugs":[[2363751990],[3708227201,3016987351,2244851822]],"tags":["GodPVE"]},{"description":"PvE: Jagged + Infinite Guard + Relentless Strikes + Surrounded/Counterattack/Flash Counter\nPvP: Any, you 1 heavy anything in the game","hash":2782325301,"name":"","plugs":[[2363751990],[1749209109]],"tags":["GodPVE"]},{"description":"PvE: corkcrew/smallbore + Assault/Light/Appended/Tac + Lead from Gold/Fieldprep/Surplus + OFA/Vorpal/Trench/Wellspring\nPvP: Fullchoke/cork/small +Assault/Accurized + Quickdraw/Surplus + Snapshot/Vorpal\nMax range stat is key with the 3.2.1 shotgun update. Looking for ~80 range.","hash":2591111628,"name":"","plugs":[[4090651448,1482024992],[791862061],[3436462433],[1546637391]],"tags":["GodPVE","GodPVP"]},{"description":"PvP: Fullchoke/cork/small + Assault/Accurized + Quickdraw/Surplus + Snapshot/Vorpal\nMax range stat is key with the 3.2.1 shotgun update. Looking for ~80 range.","hash":2591111628,"name":"","plugs":[[1047830412,4090651448,1482024992],[791862061,3142289711],[706527188,3436462433],[957782887,1546637391]],"tags":["GodPVP"]},{"description":"PvE: corkcrew/smallbore + Assault/Light/Appended/Tac + Lead from Gold/Fieldprep/Surplus + OFA/Vorpal/Trench/Wellspring","hash":2591111628,"name":"","plugs":[[4090651448,1482024992],[791862061,679225683,1087426260,106909392],[1556840489,2869569095,3436462433],[4049631843,1546637391,2360754333,3592538738]],"tags":["GodPVE"]},{"description":"PvE: corkcrew/smallbore + Assault/Light/Appended/Tac + Lead from Gold/Fieldprep/Surplus + OFA/Vorpal/Trench/Wellspring\nPvP: Fullchoke/cork/small +Assault/Accurized + Quickdraw/Surplus + Snapshot/Vorpal\nMax range stat is key with the 3.2.1 shotgun update. Looking for ~80 range.","hash":2591111628,"name":"","plugs":[[791862061],[3436462433],[1546637391]],"tags":["PVE","PVP"]},{"description":"PvE: corkcrew/smallbore + Assault/Light/Appended/Tac + Lead from Gold/Fieldprep/Surplus + OFA/Vorpal/Trench/Wellspring\nPvP: Fullchoke/cork/small +Assault/Accurized + Quickdraw/Surplus + Snapshot/Vorpal\nMax range stat is key with the 3.2.1 shotgun update. Looking for ~80 range.","hash":2591111628,"name":"","plugs":[[4090651448,1482024992],[3436462433],[1546637391]],"tags":["PVE","PVP"]},{"description":"PvP: Fullchoke/cork/small + Assault/Accurized + Quickdraw/Surplus + Snapshot/Vorpal\nMax range stat is key with the 3.2.1 shotgun update. Looking for ~80 range.","hash":2591111628,"name":"","plugs":[[791862061,3142289711],[706527188,3436462433],[957782887,1546637391]],"tags":["PVP"]},{"description":"PvP: Fullchoke/cork/small + Assault/Accurized + Quickdraw/Surplus + Snapshot/Vorpal\nMax range stat is key with the 3.2.1 shotgun update. Looking for ~80 range.","hash":2591111628,"name":"","plugs":[[1047830412,4090651448,1482024992],[706527188,3436462433],[957782887,1546637391]],"tags":["PVP"]},{"description":"PvE: corkcrew/smallbore + Assault/Light/Appended/Tac + Lead from Gold/Fieldprep/Surplus + OFA/Vorpal/Trench/Wellspring","hash":2591111628,"name":"","plugs":[[791862061,679225683,1087426260,106909392],[1556840489,2869569095,3436462433],[4049631843,1546637391,2360754333,3592538738]],"tags":["PVE"]},{"description":"PvE: corkcrew/smallbore + Assault/Light/Appended/Tac + Lead from Gold/Fieldprep/Surplus + OFA/Vorpal/Trench/Wellspring","hash":2591111628,"name":"","plugs":[[4090651448,1482024992],[1556840489,2869569095,3436462433],[4049631843,1546637391,2360754333,3592538738]],"tags":["PVE"]},{"description":"PvE: corkcrew/smallbore + Assault/Light/Appended/Tac + Lead from Gold/Fieldprep/Surplus + OFA/Vorpal/Trench/Wellspring\nPvP: Fullchoke/cork/small +Assault/Accurized + Quickdraw/Surplus + Snapshot/Vorpal\nMax range stat is key with the 3.2.1 shotgun update. Looking for ~80 range.","hash":2591111628,"name":"","plugs":[[3436462433],[1546637391]],"tags":["PVE","PVP"]},{"description":"PvP: Fullchoke/cork/small + Assault/Accurized + Quickdraw/Surplus + Snapshot/Vorpal\nMax range stat is key with the 3.2.1 shotgun update. Looking for ~80 range.","hash":2591111628,"name":"","plugs":[[706527188,3436462433],[957782887,1546637391]],"tags":["PVP"]},{"description":"PvE: corkcrew/smallbore + Assault/Light/Appended/Tac + Lead from Gold/Fieldprep/Surplus + OFA/Vorpal/Trench/Wellspring","hash":2591111628,"name":"","plugs":[[1556840489,2869569095,3436462433],[4049631843,1546637391,2360754333,3592538738]],"tags":["PVE"]},{"description":"PvE: corkcrew/smallbore + Assault/Light/Appended/Tac + Lead from Gold/Fieldprep/Surplus + OFA/Vorpal/Trench/Wellspring\nPvP: Fullchoke/cork/small +Assault/Accurized + Quickdraw/Surplus + Snapshot/Vorpal\nMax range stat is key with the 3.2.1 shotgun update. Looking for ~80 range.","hash":2591111628,"name":"","plugs":[[1546637391]],"tags":["PVE","PVP"]},{"description":"PvE: corkcrew/smallbore + Assault/Light/Appended/Tac + Lead from Gold/Fieldprep/Surplus + OFA/Vorpal/Trench/Wellspring\nPvP: Fullchoke/cork/small +Assault/Accurized + Quickdraw/Surplus + Snapshot/Vorpal\nMax range stat is key with the 3.2.1 shotgun update. Looking for ~80 range.","hash":2591111628,"name":"","plugs":[[3436462433]],"tags":["PVE","PVP"]},{"description":"PvP: Fullchoke/cork/small + Assault/Accurized + Quickdraw/Surplus + Snapshot/Vorpal\nMax range stat is key with the 3.2.1 shotgun update. Looking for ~80 range.","hash":2591111628,"name":"","plugs":[[957782887,1546637391]],"tags":["PVP"]},{"description":"PvP: Fullchoke/cork/small + Assault/Accurized + Quickdraw/Surplus + Snapshot/Vorpal\nMax range stat is key with the 3.2.1 shotgun update. Looking for ~80 range.","hash":2591111628,"name":"","plugs":[[706527188,3436462433]],"tags":["PVP"]},{"description":"PvE: corkcrew/smallbore + Assault/Light/Appended/Tac + Lead from Gold/Fieldprep/Surplus + OFA/Vorpal/Trench/Wellspring","hash":2591111628,"name":"","plugs":[[4049631843,1546637391,2360754333,3592538738]],"tags":["PVE"]},{"description":"PvE: corkcrew/smallbore + Assault/Light/Appended/Tac + Lead from Gold/Fieldprep/Surplus + OFA/Vorpal/Trench/Wellspring","hash":2591111628,"name":"","plugs":[[1556840489,2869569095,3436462433]],"tags":["PVE"]}]}